cloudflare_dns/__init__.py
cloudflare_dns/cli.py
cloudflare_dns-1.3.1.dist-info/LICENSE
cloudflare_dns-1.3.1.dist-info/METADATA
cloudflare_dns-1.3.1.dist-info/WHEEL
cloudflare_dns-1.3.1.dist-info/entry_points.txt
cloudflare_dns-1.3.1.dist-info/top_level.txt
cloudflare_dns-1.3.1.dist-info/RECORD
